wynn_api/__init__.py
wynn_api-3.2.1.dist-info/METADATA
wynn_api-3.2.1.dist-info/WHEEL
wynn_api-3.2.1.dist-info/top_level.txt
wynn_api-3.2.1.dist-info/RECORD
