Metadata-Version: 2.1
Name: wynn-api
Version: 3.2.1
Summary: A simple Python API Wrapper for the Wynncraft API
Home-page: https://github.com/Pix3lRift/wynn-api/tree/py-v3#readme
Author: PixelRift <amogus.my.to>
License: Apache-2.0
Project-URL: Source, https://github.com/Pix3lRift/wynn-api/tree/py-v3
Project-URL: Wynncraft Developers dc server, https://discord.gg/CtMKp3hG66
Project-URL: Node.js version, https://www.npmjs.com/package/wynn-api-node
Classifier: Development Status :: 5 - Production/Stable
Classifier: Intended Audience :: Developers
Classifier: License :: OSI Approved :: Apache Software License
Classifier: Natural Language :: English
Classifier: Operating System :: OS Independent
Classifier: Programming Language :: Python
Requires-Python: >=3.5
